{
 "statement": [
  {
   "action": [
    "rum:DeleteStrategy",
    "rum:DescribeStrategyDimension",
    "rum:SetStrategyStatus",
    "rum:DescribeSymbolOpenList",
    "rum:DescribeSymbolInfo",
    "rum:DescribeUploadURL",
    "rum:CheckFileWeb",
    "rum:NotifyUploadResult",
    "rum:DescribeUploadStatus",
    "rum:DeleteSymbol",
    "rum:RestoreRMonitorStack",
    "rum:DescribeRestoreRMonitor",
    "rum:BatchRestoreSpecifiedStacks",
    "rum:DescribeCrashProcessInfo",
    "rum:SendDailySingleMailReport",
    "rum:CreateDailyReportConfig",
    "rum:DescribeDailyReportConfig",
    "rum:DescribeResourceUsageDetailByProducts",
    "rum:DescribeResourceUsageDetail",
    "rum:DescribeProductUsageDetail",
    "rum:DescribeProductsFromResource",
    "rum:DescribeProductResourceList",
    "rum:DescribeProductExceed",
    "rum:DescribeOwnedResourceList",
    "rum:DescribeMAUResourceUsage",
    "rum:RemoveBindingResourceFromProduct",
    "rum:BindingResourceToProduct",
    "rum:DescribeMAUResourceUsageByProducts",
    "rum:ParseToken",
    "rum:DescribeToken",
    "rum:DescribeSystemSymbolConfig",
    "rum:DescribeRainbowConfig",
    "rum:DescribeCrashFile",
    "rum:DescribeCrashFileList",
    "rum:DescribeOverviewDashboardByTime",
    "rum:DescribeVersionDashboard",
    "rum:DescribeVersionList",
    "rum:DescribeDimensionsOverview",
    "rum:DescribeDimensions",
    "rum:DescribeMetricsQualityReportTrend",
    "rum:DescribeMetricsQualityReport",
    "rum:DescribeMetricData",
    "rum:DescribeMetricTopData",
    "rum:DescribeMetricSummary",
    "rum:DescribeMetricsFieldDistinctData",
    "rum:DescribeMetricDimensionList",
    "rum:DescribeMetricDimensionData",
    "rum:DescribeMetricsDashboardData",
    "rum:ModifyIssueTrackStatus",
    "rum:DescribeUserCustomDimensionsList",
    "rum:UpdateUserCustomDimension",
    "rum:UpdateAppDeliverConfig",
    "rum:DescribeAppDeliverHistory",
    "rum:DescribeAppDeliverConfigList",
    "rum:SetAppDeliverEnable",
    "rum:SelectAppDeliverConfigDetail",
    "rum:CreateAppDeliverConfig",
    "rum:DescribeAppDeliverDefaultConfig",
    "rum:DeleteAppDeliverConfig",
    "rum:UpdateTag",
    "rum:DescribeTag",
    "rum:CreateTag",
    "rum:CreateStrategy",
    "rum:DescribeStrategy",
    "rum:DescribeTrafficReportList",
    "rum:DescribeTrafficProblemDetail",
    "rum:DescribeMetrics",
    "rum:ExportMetricsToExcel",
    "rum:SubIssuesTask",
    "rum:SubIssuesPoll",
    "rum:DescribeUserDemoProductList",
    "rum:ResumeAndStopProducts",
    "rum:DeleteProduct",
    "rum:CreateProduct",
    "rum:CreateBusinessSystem",
    "rum:UpdateBusinessSystem",
    "rum:DeleteBusinessSystem",
    "rum:ResumeAndStopBusinessSystem",
    "rum:DescribeNetworkHttpDetail",
    "rum:DescribeNetworkHttpErrURLList",
    "rum:DescribeNetworkHttpIssueList",
    "rum:DescribeNetworkHttpReportList",
    "rum:DescribeBitMapProblemList",
    "rum:DescribeFDLeakProblemList",
    "rum:DescribeMemGraphProblemList",
    "rum:DescribeMemoryBadMallocProblemAccountDetail",
    "rum:DescribeMemoryBadMallocProblemFeatureAccounts",
    "rum:DescribeMemoryBadMallocProblemList",
    "rum:DescribeDownloadUrls",
    "rum:DescribeProblemAccountDetail",
    "rum:DescribeInOutReference",
    "rum:DescribeMemoryDetailFeatureAccountsProblem",
    "rum:DescribeMemoryDetailProblemList",
    "rum:DescribeMemoryDetailSingleReport",
    "rum:DescribeMemoryLeakProblemAccountDetail",
    "rum:DescribeMemoryLeakProblemFeatureAccounts",
    "rum:DescribeMemoryLeakProblemList",
    "rum:DescribeMemoryNativeProblemList",
    "rum:DescribeLaunchProblemDetail",
    "rum:DescribeLaunchProblemList",
    "rum:DescribeLagProblemTree",
    "rum:DescribeLagProblemAccountDetail",
    "rum:DescribeLagProblemFeatureAccounts",
    "rum:DescribeLagProblemList",
    "rum:DescribeFOOMMallocProblemDetail",
    "rum:DescribeFOOMMallocReportList",
    "rum:DescribeFOOMMallocProblemList",
    "rum:DescribeFOOMProblemDetail",
    "rum:DescribeFOOMProblemList",
    "rum:DescribeFOOMReportList",
    "rum:DescribeLagANRProblemAccountDetail",
    "rum:DescribeLagANRProblemFeatureAccounts",
    "rum:DescribeLagANRProblemList",
    "rum:DescribeApplicationExitReportList",
    "rum:DescribeApplicationExitReportDetail",
    "rum:DescribeUserClassifyDataKey",
    "rum:DescribeExceptionLogFrequency",
    "rum:DescribeExceptionDetail",
    "rum:DescribeExceptionReportList",
    "rum:DescribeAdvanceSearchEventList",
    "rum:BatchBindTagToFeature",
    "rum:BindTagToFeature",
    "rum:DescribeTagByFeature",
    "rum:DescribeUserCustom",
    "rum:DescribeIssuesDistribution",
    "rum:DescribeIssuesDistributionKeys",
    "rum:DescribeIssueSummaryDrillDown",
    "rum:DescribeIssuesStatisticsTrend",
    "rum:DescribeTopIssues",
    "rum:DescribeIssuesList",
    "rum:DescribeMonitorFieldDistinctData",
    "rum:DescribeExtendInfoKeys",
    "rum:DescribeUserCustomKey"
   ],
   "effect": "allow",
   "resource": "*"
  }
 ],
 "version": "2.0"
}