{
 "AddTime": "2020-12-01 17:52:50",
 "IsServiceLinkedRolePolicy": 0,
 "PolicyDocument": "{\"version\":\"2.0\",\"statement\":[{\"effect\":\"allow\",\"action\":[\"cos:GetService\",\"cos:GetBucket\",\"cos:HeadBucket\",\"cos:InitiateMultipartUpload\",\"cos:ListMultipartUploads\",\"cos:AbortMultipartUpload\",\"cos:ListParts\",\"cos:UploadPart\",\"cos:CompleteMultipartUpload\",\"cos:PutObject\",\"cos:GetObject\",\"cos:HeadObject\",\"cos:DeleteObject\",\"cos:AppendObject\",\"cos:PutObjectACL\",\"cos:PutLiveChannel\",\"cos:ListLiveChannels\",\"cos:DeleteLiveChannel\",\"cos:GetLiveChannel\",\"cos:PostVodPlayList\",\"cos:GetVodPlayList\",\"cam:ListUsers\"],\"resource\":\"*\"}]}",
 "PolicyName": "QcloudAccessForISSRole",
 "PresetAlias": "",
 "Type": 2,
 "UpdateTime": "2022-08-24 10:55:56"
}