{
 "AddTime": "2024-11-14 22:01:26",
 "IsServiceLinkedRolePolicy": 0,
 "PolicyDocument": "{\"statement\":[{\"action\":[\"ioa:DescribeDeviceCommonConfig\",\"ioa:DescribeProfileField\",\"ioa:DescribeGroupSyncSetting\"],\"effect\":\"allow\",\"resource\":\"*\"},{\"action\":[\"ioa:DescribeDevice\",\"ioa:DescribeDeviceInfo\",\"ioa:DescribeDeviceGroup\",\"ioa:DescribeDevices\",\"ioa:DescribeDeviceGroups\",\"ioa:DescribeDevicesInfo\",\"ioa:DescribeGroupDevices\",\"ioa:DescribeDeviceGroupTree\",\"ioa:DescribeDeviceChildGroups\",\"ioa:DescribeDeviceTags\",\"ioa:DescribeDeviceVirtualGroups\",\"ioa:DescribeVirtualDevices\",\"ioa:DescribeAutoVirtualGroupRule\",\"ioa:DescribeAutoVirtualGroupRuleItems\",\"ioa:DescribeRootGroupId\",\"ioa:DescribeCommonConfigs\"],\"effect\":\"allow\",\"resource\":\"*\"}],\"version\":\"2.0\"}",
 "PolicyName": "QcloudIOAAssetsReadOnlyAccess",
 "PresetAlias": "",
 "Type": 2,
 "UpdateTime": "2024-11-14 22:01:26"
}